cache_lib/__init__.py
cacheline-0.0.1.dist-info/METADATA
cacheline-0.0.1.dist-info/WHEEL
cacheline-0.0.1.dist-info/RECORD
