Metadata-Version: 2.1
Name: cacheline
Version: 0.0.1
Summary: 
Author: cache-missing
Author-email: cache@cache-miss.tech
Requires-Python: >=3.6,<4.0
Classifier: Programming Language :: Python :: 3
Classifier: Programming Language :: Python :: 3.6
Classifier: Programming Language :: Python :: 3.7
Classifier: Programming Language :: Python :: 3.8
Classifier: Programming Language :: Python :: 3.9
Classifier: Programming Language :: Python :: 3.10
Classifier: Programming Language :: Python :: 3.11
Requires-Dist: pybind11 (>=2.11.1,<3.0.0)
